oban/__init__.py
oban/__main__.py
oban/_backoff.py
oban/_config.py
oban/_executor.py
oban/_extensions.py
oban/_leader.py
oban/_lifeline.py
oban/_notifier.py
oban/_producer.py
oban/_pruner.py
oban/_query.py
oban/_recorded.py
oban/_refresher.py
oban/_scheduler.py
oban/_stager.py
oban/_worker.py
oban/cli.py
oban/decorators.py
oban/job.py
oban/oban.py
oban/py.typed
oban/schema.py
oban/testing.py
oban/queries/__init__.py
oban/queries/ack_job.sql
oban/queries/all_jobs.sql
oban/queries/cancel_many_jobs.sql
oban/queries/cleanup_expired_leaders.sql
oban/queries/cleanup_expired_producers.sql
oban/queries/delete_many_jobs.sql
oban/queries/delete_producer.sql
oban/queries/elect_leader.sql
oban/queries/fetch_jobs.sql
oban/queries/get_job.sql
oban/queries/insert_job.sql
oban/queries/insert_producer.sql
oban/queries/install.sql
oban/queries/prune_jobs.sql
oban/queries/reelect_leader.sql
oban/queries/refresh_producers.sql
oban/queries/rescue_jobs.sql
oban/queries/reset.sql
oban/queries/resign_leader.sql
oban/queries/retry_many_jobs.sql
oban/queries/stage_jobs.sql
oban/queries/uninstall.sql
oban/queries/update_job.sql
oban/queries/update_producer.sql
oban/queries/verify_structure.sql
oban/telemetry/__init__.py
oban/telemetry/core.py
oban/telemetry/logger.py
oban-0.5.0.dist-info/licenses/LICENSE.txt
oban-0.5.0.dist-info/METADATA
oban-0.5.0.dist-info/WHEEL
oban-0.5.0.dist-info/entry_points.txt
oban-0.5.0.dist-info/top_level.txt
oban-0.5.0.dist-info/RECORD
