Metadata-Version: 2.4
Name: oban
Version: 0.5.0
Summary: Job orchestration framework, backed by PostgreSQL.
Author-email: "Soren, LLC" <support@oban.pro>
License-Expression: Apache-2.0
Project-URL: Homepage, https://oban.pro
Project-URL: Documentation, https://oban.pro/docs/py
Project-URL: Repository, https://github.com/oban-bg/oban-py
Project-URL: Changelog, https://github.com/oban-bg/oban-py/blob/main/CHANGELOG.md
Project-URL: Issues, https://github.com/oban-bg/oban-py/issues
Keywords: jobs,queue,background,async,postgresql,worker,cron,scheduling,task-queue
Classifier: Development Status :: 4 - Beta
Classifier: Framework :: AsyncIO
Classifier: Intended Audience :: Developers
Classifier: Operating System :: OS Independent
Classifier: Programming Language :: Python :: 3
Classifier: Programming Language :: Python :: 3.12
Classifier: Programming Language :: Python :: 3.13
Classifier: Programming Language :: Python :: 3.14
Classifier: Topic :: Software Development :: Libraries :: Python Modules
Classifier: Topic :: System :: Distributed Computing
Classifier: Typing :: Typed
Requires-Python: >=3.12
License-File: LICENSE.txt
Requires-Dist: click>=8.1.0
Requires-Dist: erlpack>=1.0.0
Requires-Dist: orjson>=3.11.4
Requires-Dist: psycopg-pool>=3.2.6
Requires-Dist: psycopg[binary]>=3.2.13
Requires-Dist: uvloop>=0.22.0
Dynamic: license-file
